LICENSE
MANIFEST.in
README.rst
setup.py
rlib_store.egg-info/PKG-INFO
rlib_store.egg-info/SOURCES.txt
rlib_store.egg-info/dependency_links.txt
rlib_store.egg-info/not-zip-safe
rlib_store.egg-info/requires.txt
rlib_store.egg-info/top_level.txt
rstore/__init__.py
rstore/_psql_store.py
rstore/_redis_store.py
rstore/_sqlite_store.py